gendgn/__init__.py
gendgn/batch_eval.py
gendgn/exe_wwr_constr.py
gendgn/pmtrz_wwr_constr.py
gendgn/sample_variants.py
gendgn/settings.py
gendgn/data/gendgn.egg-info/PKG-INFO
gendgn/data/gendgn.egg-info/SOURCES.txt
gendgn/data/gendgn.egg-info/dependency_links.txt
gendgn/data/gendgn.egg-info/entry_points.txt
gendgn/data/gendgn.egg-info/requires.txt
gendgn/data/gendgn.egg-info/top_level.txt
gendgn/data/json/pmtrc_mod_schema.json
gendgn-0.0.8.dist-info/LICENSE
gendgn-0.0.8.dist-info/METADATA
gendgn-0.0.8.dist-info/WHEEL
gendgn-0.0.8.dist-info/entry_points.txt
gendgn-0.0.8.dist-info/top_level.txt
gendgn-0.0.8.dist-info/RECORD
