Metadata-Version: 2.2
Name: gendgn
Version: 0.0.8
Summary: Python-based command line tool for generative design using IFC file format
Author-email: Kian Wee CHEN <chenkianwee@gmail.com>
Project-URL: Homepage, https://github.com/chenkianwee/gendgn
Project-URL: Bug Tracker, https://github.com/chenkianwee/gendgn/issues
Classifier: License :: OSI Approved :: GNU General Public License v3 (GPLv3)
Classifier: Programming Language :: Python :: 3.10
Classifier: Operating System :: OS Independent
Requires-Python: <3.13,>=3.10
License-File: LICENSE
Requires-Dist: ifc2osmod==0.0.7
Requires-Dist: jsonschema==4.23.0
Requires-Dist: pymoo==0.6.1.3
Provides-Extra: viewer3d
Requires-Dist: ifc2osmod[viewer3d]==0.0.6; extra == "viewer3d"
